<?xml version="1.0" encoding="utf-8" ?>
<GameItems RootImagePath="Resources/Sprites/Items/">
  <GameItem ID="-1"
            Type="Weapon"
            Name=""
            ImageName="Black.png"
            Description="ыasd">
    <Weapon MinDamage="1"
            MinMinDamage="1"
            MaxDamage="3"
            MaxMaxDamage="3"/>
  </GameItem>
  <GameItem ID="-2"
            Type="Armor"
            Name=""
            ImageName="Black.png"
            Description="a">
    <Armor PlusArmor="0"/>
  </GameItem>
  <GameItem ID="1"
            Type="Weapon"
            Name="woodStick"
            ImageName="woodStick.png"
            Description="a">
    <Weapon MinDamage="5"
            MinMinDamage="5"
            MaxDamage="10"
            MaxMaxDamage="10"/>
  </GameItem>
  
  <GameItem ID="3"
            Type="Armor"
            Name="dragonArmor"
            ImageName="dragonArmor.png"
            Description="">
    <Armor PlusArmor="5"/>
  </GameItem>
  
  <GameItem ID="2"
            Type="Weapon"
            Name="katana"
            ImageName="katana.png"
            Description="a">
    <Weapon MinDamage="5"
            MinMinDamage="1"
            MaxDamage="12"
            MaxMaxDamage="17"/>
  </GameItem>
  <GameItem ID="5"
            Type="Miscellaneous"
            Name="mussel"
            ImageName="mussel.png"
            Description="Lorem ipsum dolor sit amet, alii aliquid repudiandae in nam, cum ad malis dicam nostro. Cum veri erant melius ut. Duo id dicat soluta. Ea suas lucilius sit, impetus similique voluptaria an his, ne nec graecis indoctum. Magna nemore cu sit, mei et purto legendos theophrastus. Eam recteque adipiscing ut, eos urbanitas intellegat expetendis et, ne est admodum placerat contentiones. Nostrum recusabo in has, ad lorem quaerendum pro. Errem persius quaestio has ne, movet offendit platonem mei eu. Vel ad minim error invenire, nam te primis timeam discere, ad idque solet accusam per.">
  </GameItem>
  <GameItem ID="4"
            Type="Potion"
            Name="broadsword"
            ImageName="broadsword.png"
            Description="a">
    <Potion HitPointsToHealHP="2"
            HitPointsToHealMP="2"/>
  </GameItem>
</GameItems>